{
  "char_to_int": {
    "!": 18,
    "#": 33,
    "$": 9,
    "%": 13,
    "(": 30,
    ")": 23,
    "+": 0,
    "-": 17,
    "1": 11,
    "2": 29,
    "3": 12,
    "4": 2,
    "5": 24,
    "6": 28,
    "7": 31,
    "8": 20,
    "=": 16,
    "C": 25,
    "F": 10,
    "H": 26,
    "I": 6,
    "N": 4,
    "O": 14,
    "P": 7,
    "S": 27,
    "X": 8,
    "Y": 32,
    "[": 19,
    "]": 15,
    "c": 3,
    "n": 5,
    "o": 21,
    "p": 1,
    "s": 22
  },
  "int_to_char": {
    "0": "+",
    "1": "p",
    "10": "F",
    "11": "1",
    "12": "3",
    "13": "%",
    "14": "O",
    "15": "]",
    "16": "=",
    "17": "-",
    "18": "!",
    "19": "[",
    "2": "4",
    "20": "8",
    "21": "o",
    "22": "s",
    "23": ")",
    "24": "5",
    "25": "C",
    "26": "H",
    "27": "S",
    "28": "6",
    "29": "2",
    "3": "c",
    "30": "(",
    "31": "7",
    "32": "Y",
    "33": "#",
    "4": "N",
    "5": "n",
    "6": "I",
    "7": "P",
    "8": "X",
    "9": "$"
  }
}
